README.md
setup.py
magicreq/__init__.py
magicreq/bootstrap.py
magicreq.egg-info/PKG-INFO
magicreq.egg-info/SOURCES.txt
magicreq.egg-info/dependency_links.txt
magicreq.egg-info/top_level.txt
test/test.py