Metadata-Version: 1.2
Name: magicreq
Version: 0.6.0
Summary: magicreq (Magic Requirements): Depend on packages without having to install them.
Home-page: https://github.com/reversefold/magicreq
Author: Justin Patrin
Author-email: papercrane@reversefold.com
Maintainer: Justin Patrin
Maintainer-email: papercrane@reversefold.com
License: UNKNOWN
Platform: UNKNOWN
